{"proposedName": "Frontend P99 Latency", "proposedPrometheusQueryString": "label_join((histogram_quantile(0.99, sum(rate(istio_request_duration_milliseconds_bucket{destination_workload=\"frontend\", reporter=\"source\"}[1m])) by (le, destination_workload, destination_workload_namespace)) / 1000) or histogram_quantile(0.99, sum(rate(istio_request_duration_seconds_bucket{destination_workload=\"frontend\", reporter=\"source\"}[1m])) by (le, destination_workload, destination_workload_namespace)), \"destination_workload_var\", \".\", \"destination_workload\", \"destination_workload_namespace\")", "proposedThreshold": "0.001", "description": "The 99th percentile of latency on the frontend"}
{"proposedName": "Ad service P99 Latency", "proposedPrometheusQueryString": "label_join((histogram_quantile(0.99, sum(rate(istio_request_duration_milliseconds_bucket{destination_workload=\"adservice\", reporter=\"source\"}[1m])) by (le, destination_workload, destination_workload_namespace)) / 1000) or histogram_quantile(0.99, sum(rate(istio_request_duration_seconds_bucket{destination_workload=\"adservice\", reporter=\"source\"}[1m])) by (le, destination_workload, destination_workload_namespace)), \"destination_workload_var\", \".\", \"destination_workload\", \"destination_workload_namespace\")", "proposedThreshold": "1", "description": "The 99th percentile of latency on the adservice"}
{"proposedName": "Erroneous Frontend P99 Latency", "proposedPrometheusQueryString": "", "proposedThreshold": "1", "description": "The 99th percentile of latency on the frontend"}
